Metadata-Version: 1.1
Name: cardholder
Version: 0.0.2
Summary: Rotary Card Holder GUI
Home-page: http://github.com/dallaszkorben/cardholder
Author: dallaszkorben
Author-email: dallaszkorben@gmail.com
License: MIT
Platform: UNKNOWN
Classifier: Programming Language :: Python
Classifier: Programming Language :: Python :: 3
Classifier: Operating System :: OS Independent
